SuperSaaS/Client.py
SuperSaaS/Error.py
SuperSaaS/__init__.py
SuperSaaS/API/Appointments.py
SuperSaaS/API/BaseApi.py
SuperSaaS/API/Forms.py
SuperSaaS/API/Groups.py
SuperSaaS/API/Promotions.py
SuperSaaS/API/Schedules.py
SuperSaaS/API/Users.py
SuperSaaS/API/__init__.py
SuperSaaS/Models/Appointment.py
SuperSaaS/Models/BaseModel.py
SuperSaaS/Models/FieldList.py
SuperSaaS/Models/Form.py
SuperSaaS/Models/Group.py
SuperSaaS/Models/Promotion.py
SuperSaaS/Models/Resource.py
SuperSaaS/Models/Schedule.py
SuperSaaS/Models/Slot.py
SuperSaaS/Models/SuperForm.py
SuperSaaS/Models/User.py
SuperSaaS/Models/__init__.py
test/AppointmentsTest.py
test/ClientTest.py
test/FormsTest.py
test/GroupsTest.py
test/Helper.py
test/PromotionsTest.py
test/SchedulesTest.py
test/UsersTest.py
test/__init__.py
supersaas_api_client-2.0.0.dist-info/LICENSE
supersaas_api_client-2.0.0.dist-info/METADATA
supersaas_api_client-2.0.0.dist-info/WHEEL
supersaas_api_client-2.0.0.dist-info/top_level.txt
supersaas_api_client-2.0.0.dist-info/RECORD
