Metadata-Version: 2.1
Name: supersaas-api-client
Version: 2.0.0
Summary: Online bookings/appointments/calendars using the SuperSaaS scheduling platform  - https://supersaas.com
Home-page: https://www.supersaas.com
Author: Kaarle Kulvik
Author-email: dev@supersaas.com
License: MIT
Project-URL: Homepage, https://www.supersaas.com
Project-URL: Issues, https://github.com/SuperSaaS/supersaas-python-api-client/issues
Project-URL: Documentation, https://www.supersaas.com/info/dev
Project-URL: Source, https://github.com/SuperSaaS/supersaas-python-api-client
Keywords: online appointment schedule,booking calendar,appointment book,reservation system,scheduling software,online booking system,scheduling system,supersaas
Classifier: Development Status :: 4 - Beta
Classifier: License :: OSI Approved :: MIT License
Classifier: Programming Language :: Python
Classifier: Programming Language :: Python :: 3
Classifier: Programming Language :: Python :: 3 :: Only
Classifier: Topic :: Office/Business :: Scheduling
Requires-Python: >=3.8
License-File: LICENSE
